sloth_ci_ext_notifications.py
sloth_ci_ext_notifications-1.0.8.dist-info/LICENSE
sloth_ci_ext_notifications-1.0.8.dist-info/WHEEL
sloth_ci_ext_notifications-1.0.8.dist-info/METADATA
sloth_ci_ext_notifications-1.0.8.dist-info/RECORD
